setup.py
buky_probability/Binomialdistribution.py
buky_probability/Gaussiandistribution.py
buky_probability/Generaldistribution.py
buky_probability/__init__.py
buky_probability.egg-info/PKG-INFO
buky_probability.egg-info/SOURCES.txt
buky_probability.egg-info/dependency_links.txt
buky_probability.egg-info/not-zip-safe
buky_probability.egg-info/top_level.txt