Metadata-Version: 1.0
Name: buky-probability
Version: 0.1
Summary: Gaussian and Binomial distribution
Home-page: UNKNOWN
Author: Abubeker
Author-email: abukie969@gmail.com
License: UNKNOWN
Platform: UNKNOWN
